vpn/__init__.py
vpn/main.py
vpn/requirements.txt
vpn/models/config.py
vpn/models/exceptions.py
vpn/models/image_factory.py
vpn/models/logger.py
vpn/models/route53.py
vpn/models/server.py
vpn/models/util.py
vpn_server-1.7.1.dist-info/LICENSE
vpn_server-1.7.1.dist-info/METADATA
vpn_server-1.7.1.dist-info/WHEEL
vpn_server-1.7.1.dist-info/top_level.txt
vpn_server-1.7.1.dist-info/RECORD
