Metadata-Version: 2.1
Name: vpn-server
Version: 1.7.1
Summary: Create an on-demand VPN Server running OpenVPN using AWS EC2
Author-email: Vignesh Rao <svignesh1793@gmail.com>
License: MIT License
Project-URL: Homepage, https://github.com/thevickypedia/vpn-server
Project-URL: Docs, https://thevickypedia.github.io/vpn-server
Project-URL: Source, https://github.com/thevickypedia/vpn-server
Project-URL: Bug Tracker, https://github.com/thevickypedia/vpn-server/issues
Project-URL: Release Notes, https://github.com/thevickypedia/vpn-server/blob/main/release_notes.rst
Keywords: openvpn-server,vpn-server,aws-ec2
Classifier: Development Status :: 5 - Production/Stable
Classifier: Intended Audience :: Information Technology
Classifier: Operating System :: OS Independent
Classifier: License :: OSI Approved :: MIT License
Classifier: Programming Language :: Python :: 3 :: Only
Classifier: Topic :: System :: Networking :: Firewalls
Requires-Python: >=3.8
License-File: LICENSE
Requires-Dist: boto3
Requires-Dist: botocore
Requires-Dist: inflect
Requires-Dist: paramiko ==3.3.1
Requires-Dist: paramiko-expect ==0.3.5
Requires-Dist: pydantic ==2.4.*
Requires-Dist: pydantic-settings ==2.0.*
Requires-Dist: requests
Provides-Extra: dev
Requires-Dist: pre-commit ; extra == 'dev'
